fb_video/__init__.py
fb_video/scraper.py
fb_video-0.1.6.dist-info/METADATA
fb_video-0.1.6.dist-info/WHEEL
fb_video-0.1.6.dist-info/entry_points.txt
fb_video-0.1.6.dist-info/top_level.txt
fb_video-0.1.6.dist-info/RECORD
