Metadata-Version: 2.2
Name: fb-video
Version: 0.1.6
Summary: A Facebook video information scraper by Kehem IT
Home-page: https://github.com/kehem/fb-download
Author: Kehem IT
Author-email: support@kehem.com
Classifier: Programming Language :: Python :: 3
Classifier: License :: OSI Approved :: MIT License
Classifier: Operating System :: OS Independent
Requires-Python: >=3.6
Requires-Dist: requests
Dynamic: author
Dynamic: author-email
Dynamic: classifier
Dynamic: description
Dynamic: description-content-type
Dynamic: home-page
Dynamic: requires-dist
Dynamic: requires-python
Dynamic: summary
